{"cameraMode":{"drawMode":0,"name":"Shaded","section":"Shading Mode"},"sceneLighting":true,"audioPlay":false,"sceneViewState":{"m_AlwaysRefresh":false,"showFog":true,"showSkybox":true,"showFlares":true,"showImageEffects":true,"showParticleSystems":true,"showVisualEffectGraphs":true,"m_FxEnabled":true},"in2DMode":false,"pivot":{"x":-0.8837059736251831,"y":6.661992073059082,"z":-38.86720275878906},"rotation":{"x":0.007633384317159653,"y":-0.9904898405075073,"z":0.12275971472263336,"w":0.06159603223204613},"size":38.36848449707031,"orthographic":false}